poetry_plugin_dotenv/__init__.py
poetry_plugin_dotenv/commands.py
poetry_plugin_dotenv/configurator.py
poetry_plugin_dotenv/dotenv/__init__.py
poetry_plugin_dotenv/dotenv/core.py
poetry_plugin_dotenv/dotenv/parsers.py
poetry_plugin_dotenv/dotenv/variables.py
poetry_plugin_dotenv/exceptions.py
poetry_plugin_dotenv/loader.py
poetry_plugin_dotenv/logging.py
poetry_plugin_dotenv/plugin.py
poetry_plugin_dotenv/py.typed
poetry_plugin_dotenv-3.1.1.dist-info/METADATA
poetry_plugin_dotenv-3.1.1.dist-info/WHEEL
poetry_plugin_dotenv-3.1.1.dist-info/entry_points.txt
poetry_plugin_dotenv-3.1.1.dist-info/licenses/LICENSE
poetry_plugin_dotenv-3.1.1.dist-info/RECORD
