Metadata-Version: 2.4
Name: poetry-plugin-dotenv
Version: 3.1.1
Summary: poetry-plugin-dotenv - is the plugin that automatically loads environment variables from a dotenv file into the environment before poetry commands are run.
License: MIT
License-File: LICENSE
Keywords: config,configuration,configuration-management,cross-platform,dotenv,env,hacktoberfest,plugin,plugins,poetry,poetry-plugin,poetry-plugins,pypi,python
Author: Volodymyr Pivoshenko
Author-email: volodymyr.pivoshenko@gmail.com
Maintainer: Volodymyr Pivoshenko
Maintainer-email: volodymyr.pivoshenko@gmail.com
Requires-Python: >=3.9,<4.0
Classifier: Development Status :: 5 - Production/Stable
Classifier: Environment :: Other Environment
Classifier: Intended Audience :: Developers
Classifier: Intended Audience :: Information Technology
Classifier: License :: OSI Approved :: MIT License
Classifier: Natural Language :: English
Classifier: Operating System :: OS Independent
Classifier: Programming Language :: Python
Classifier: Programming Language :: Python :: 3
Classifier: Programming Language :: Python :: 3.9
Classifier: Programming Language :: Python :: 3.10
Classifier: Programming Language :: Python :: 3.11
Classifier: Programming Language :: Python :: 3.12
Classifier: Programming Language :: Python :: 3.13
Classifier: Programming Language :: Python :: 3.14
Classifier: Programming Language :: Python :: 3.8
Classifier: Topic :: Scientific/Engineering
Classifier: Topic :: Software Development
Classifier: Topic :: Software Development :: Libraries
Classifier: Topic :: Software Development :: Libraries :: Python Modules
Requires-Dist: poetry (>=1.5.0,<3.0.0)
Project-URL: Documentation, https://github.com/pivoshenko/poetry-plugin-dotenv
Project-URL: Homepage, https://github.com/pivoshenko/poetry-plugin-dotenv
Project-URL: Issues, https://github.com/pivoshenko/poetry-plugin-dotenv/issues
Project-URL: Repository, https://github.com/pivoshenko/poetry-plugin-dotenv
Project-URL: Releases, https://github.com/pivoshenko/poetry-plugin-dotenv/releases
